{
  "name": "SocietyExpense",
  "base": "SocietyBaseModel",
  "idInjection": false,
  "options": {
    "validateUpsert": true
  },
  "mysql": {
    "schema": "society",
    "table": "society_expense"
  },
  "properties": {
    "id": {
      "type": "Number",
      "id": true,
      "required": true,
      "length": null,
      "precision": 10,
        "generated": true,
      "scale": 0,
      "mysql": {
        "columnName": "id",
        "dataType": "int",
        "dataLength": null,
        "dataPrecision": 10,
        "dataScale": 0,
        "nullable": "N"
      },
      "_selectable": false
    },
    "debitAmount": {
      "type": "Number",
      "required": false,
      "length": null,
      "precision": 22,
      "scale": null,
      "mysql": {
        "columnName": "debit_amount",
        "dataType": "double",
        "dataLength": null,
        "dataPrecision": 22,
        "dataScale": null,
        "nullable": "Y"
      },
      "_selectable": false
    },
      "creditAmount": {
          "type": "Number",
          "required": false,
          "length": null,
          "precision": 22,
          "scale": null,
          "mysql": {
              "columnName": "credit_amount",
              "dataType": "double",
              "dataLength": null,
              "dataPrecision": 22,
              "dataScale": null,
              "nullable": "Y"
          },
          "_selectable": false
      },
    "description": {
      "type": "String",
      "required": false,
      "length": 50,
      "precision": null,
        "required": true,
      "scale": null,
      "mysql": {
        "columnName": "description",
        "dataType": "varchar",
        "dataLength": 50,
        "dataPrecision": null,
        "dataScale": null,
        "nullable": "N"
      },
      "_selectable": true
    },
    "createDate": {
      "type": "Date",
      "required": true,
      "length": null,
      "precision": null,
      "scale": null,
      "mysql": {
        "columnName": "create_date",
        "dataType": "datetime",
        "dataLength": null,
        "dataPrecision": null,
        "dataScale": null,
        "nullable": "N"
      },
      "_selectable": false
    }
  },
  "validations": [],
  "relations": {},
  "acls": [],
  "methods": {}
}
